freddy/__init__.py
freddy/_base_client.py
freddy/async_client.py
freddy/client.py
freddy/exceptions.py
freddy/files.py
freddy/images.py
freddy/models.py
freddy/responses.py
freddy/types.py
freddy/vector_stores.py
aitronos_freddy-0.1.0.dist-info/LICENSE
aitronos_freddy-0.1.0.dist-info/METADATA
aitronos_freddy-0.1.0.dist-info/WHEEL
aitronos_freddy-0.1.0.dist-info/RECORD
