Metadata-Version: 2.3
Name: aitronos-freddy
Version: 0.1.0
Summary: Official Python SDK for Freddy AI Assistant API
License: MIT
Keywords: ai,assistant,api,freddy,llm
Author: Aitronos
Author-email: phillip.loacker@aitronos.com
Requires-Python: >=3.11,<4.0
Classifier: License :: OSI Approved :: MIT License
Classifier: Programming Language :: Python :: 3
Classifier: Programming Language :: Python :: 3.11
Classifier: Programming Language :: Python :: 3.12
Classifier: Programming Language :: Python :: 3.13
Requires-Dist: httpx (>=0.25.0,<0.26.0)
Requires-Dist: pydantic (>=2.9.0,<3.0.0)
Requires-Dist: typing-extensions (>=4.8.0,<5.0.0)
Project-URL: Documentation, https://freddy-api.aitronos.com/docs
Project-URL: Homepage, https://freddy-api.aitronos.com
Project-URL: Repository, https://github.com/aitronos/freddy-python
